wheezy.template-0.1.184-py3.8-nspkg.pth
wheezy/template/__init__.py
wheezy/template/builder.py
wheezy/template/comp.py
wheezy/template/compiler.py
wheezy/template/console.py
wheezy/template/engine.py
wheezy/template/lexer.py
wheezy/template/loader.py
wheezy/template/parser.py
wheezy/template/preprocessor.py
wheezy/template/utils.py
wheezy/template/ext/__init__.py
wheezy/template/ext/code.py
wheezy/template/ext/core.py
wheezy/template/ext/determined.py
wheezy.template-0.1.184.dist-info/LICENSE
wheezy.template-0.1.184.dist-info/METADATA
wheezy.template-0.1.184.dist-info/WHEEL
wheezy.template-0.1.184.dist-info/entry_points.txt
wheezy.template-0.1.184.dist-info/namespace_packages.txt
wheezy.template-0.1.184.dist-info/top_level.txt
wheezy.template-0.1.184.dist-info/RECORD
